order_followup/__init__.py
order_followup/__main__.py
order_followup/main.py
order_followup/queries.py
order_followup/utilities.py
order_followup/helpers/__init__.py
order_followup/helpers/queries.py
order_followup/helpers/utilities.py
order_followup-1.0.5.dist-info/LICENSE
order_followup-1.0.5.dist-info/METADATA
order_followup-1.0.5.dist-info/WHEEL
order_followup-1.0.5.dist-info/top_level.txt
order_followup-1.0.5.dist-info/RECORD
