Metadata-Version: 2.1
Name: order-followup
Version: 1.0.5
Summary: Exports a csv file of email subscribers using the Shopify API
Home-page: UNKNOWN
Author: Russ Nastala
License: MIT
Platform: UNKNOWN
Classifier: License :: OSI Approved :: MIT License
Requires-Python: ~=3.8
License-File: LICENSE
Requires-Dist: ShopifyAPI ==12.5.0
Requires-Dist: pytz ==2024.1
Requires-Dist: requests ==2.32.3
